Testing/Test1/MIPS32.v
//MIPS32 Basic Implmentation 
//Engineer : Sat Patel 

module MIPS32 ( clk1, clk2 ) ; 

//Using two phase clock, for avoiding clashes and clock skews 
input clk1, clk2 ; 
//Register Bank 
reg [31:0] RegBank [31:0] ; //Register bank ( 32 X 32 ) 

//Memory - 1024 x 32 
reg [31:0] Mem [1023:0] ; 

//Declaring the opcodes for the various instructions 
parameter ADD = 6'b000000 , SUB = 6'b000001, AND = 6'b000010, 
	OR = 6'b000011, SLT = 6'b000100, MUL = 6'b000101, HLT = 6'b111111, 
	LW = 6'b001000, SW = 6'b001001, ADDI = 6'b001010, SUBI = 6'b001011, 
	SLTI = 6'b001100, BNEQZ = 6'b001101, BEQZ = 6'b001110 ; 
	

//Types of instructions 
parameter RR_ALU = 3'b000, RM_ALU = 3'b001, LOAD = 3'b010, 
		STORE = 3'b011, BRANCH = 3'b100, HALT = 3'b101 ; 
		
reg [2:0] ID_EX_type, EX_MEM_type, MEM_WB_type ; 
		
reg HALTED ; 
//Set after HLT instruction is completed - in WB stage 

reg TAKEN_BRANCH ; 
//Required to disable instructions after branch 


//Defining intermediate latches between Instruction Fetch stage 
//and Instruction Decode stage 

reg [31:0] PC, IF_ID_IR, IF_ID_NPC ; 
//PC- Program Counter 
//IR - Instruction Register 
//NPC - Next Program Counter 

//Defining intermediate latches between Instruction Decode stage and 
//Execute stage 
reg [31:0] ID_EX_IR, ID_EX_NPC, ID_EX_A, ID_EX_B, ID_EX_Imm ; 

//Defining intermediate latches between Execute Stage and Memory Stage 
reg [31:0] EX_MEM_IR, EX_MEM_ALUOut, EX_MEM_B ; 
reg EX_MEM_cond ; 

//Defining intermediate latches between Memory Stage and Write back stage 
reg [31:0] MEM_WB_IR, MEM_WB_ALUOut, MEM_WB_LMD ; 

//Instruction Fetch Stage --- Stage 1 

always @ ( posedge clk1 ) 

	if ( HALTED == 0 ) 
		begin 
			if(((EX_MEM_IR[31:26] == BEQZ) && (EX_MEM_cond == 1)) || ((EX_MEM_IR[31:26] == BNEQZ) && (EX_MEM_cond == 0))) 
				begin 
					IF_ID_IR <= Mem[EX_MEM_ALUOut] ; 
					TAKEN_BRANCH <= 1'b1 ; 
					IF_ID_NPC <= EX_MEM_ALUOut + 1 ; 
					PC <= EX_MEM_ALUOut + 1 ; 
				end 
		else 
			begin 
				IF_ID_IR <= Mem[PC] ; 
				IF_ID_NPC <= PC + 1 ; 
				PC <= PC + 1 ; 
			end 
		end 

//Instruction Decode Stage or Register Fetch stage --- Stage 2

always @ ( posedge clk2 ) 

	if(HALTED == 0 ) 
		begin 
			if(IF_ID_IR[25:21] == 5'b00000) 
				ID_EX_A <= 0 ; 
			else 
				ID_EX_A <= RegBank[IF_ID_IR[25:21]] ; //"rs" 
			
			if(IF_ID_IR[20:16] == 5'b00000) 
				ID_EX_B <= 0 ; 
			else 
				ID_EX_B <= RegBank[IF_ID_IR[20:16]] ; //"rt" 
			
			ID_EX_NPC <= IF_ID_NPC ; 
			ID_EX_IR <= IF_ID_IR ; 
			ID_EX_Imm <= { {16{IF_ID_IR[15]} } , {IF_ID_IR[15:0] }} ; 
			
		case (IF_ID_IR[31:26]) 
		
			ADD, SUB, AND, OR, SLT, MUL:  ID_EX_type <= RR_ALU ; 
			ADDI, SUBI, SLTI: 			  ID_EX_type <= RM_ALU ; 
			LW: 						  ID_EX_type <= LOAD   ;
			SW: 						  ID_EX_type <= STORE  ;	 
			BNEQZ, BEQZ: 				  ID_EX_type <= BRANCH ;
			HLT: 						  ID_EX_type <= HALT   ;
			default: 					  ID_EX_type <= HALT   ;	//In case of invalid opcode 
			
		endcase 
	end 

//Execution Stage or Effective Address Calculation --- Stage 3 

always @ (posedge clk1) 
	
	if(HALTED == 0) 
	begin 
	
		EX_MEM_type <= ID_EX_type ; 
		EX_MEM_IR <= ID_EX_IR ; 
		TAKEN_BRANCH <= 0 ; 
		
		case ( ID_EX_type) //Decoding the type of instruction format 
		
		RR_ALU: begin 	//Register to Register type instructions 
					case(ID_EX_IR[31:26]) // opcode for Register to Register ALU instructions 
						ADD: EX_MEM_ALUOut <= ID_EX_A + ID_EX_B ; 
						SUB: EX_MEM_ALUOut <= ID_EX_A - ID_EX_B ; 
						AND: EX_MEM_ALUOut <= ID_EX_A & ID_EX_B ; 
						OR : EX_MEM_ALUOut <= ID_EX_A | ID_EX_B ; 
						SLT: EX_MEM_ALUOut <= ID_EX_A < ID_EX_B ; 
						MUL: EX_MEM_ALUOut <= ID_EX_A * ID_EX_B ; 
						default: EX_MEM_ALUOut <= 32'hxxxxxxxx ; 
					endcase 
				end 
		RM_ALU: begin //Register to memory type instructions 
					case( ID_EX_IR[31:26]) // opcode for Register to Memory ALU isntructions 
						ADDI: EX_MEM_ALUOut <= ID_EX_A + ID_EX_Imm ; 
						SUBI: EX_MEM_ALUOut <= ID_EX_A - ID_EX_Imm ; 
						SLTI: EX_MEM_ALUOut <= ID_EX_A < ID_EX_Imm ; 
						default: EX_MEM_ALUOut <= 32'hxxxxxxxx ; 
					endcase 
				end 
		LOAD, STORE: begin //Load and store instructions 
						EX_MEM_ALUOut <= ID_EX_A + ID_EX_Imm ; 
						EX_MEM_B <= ID_EX_B ; 
					end 
		BRANCH: begin 
					EX_MEM_ALUOut <= ID_EX_NPC + ID_EX_Imm ; 
					EX_MEM_cond <= (ID_EX_A == 0 ) ; 
				end 
		endcase 
		
	end 
	

//Memory access stage or Branch Completion  --- Stage 4 

always @ (posedge clk2) 

	if(HALTED == 0 ) 
	
	begin 
		MEM_WB_type <= EX_MEM_type ; 
		MEM_WB_IR <= EX_MEM_IR ; 
		
		case (EX_MEM_type) 
		
			RR_ALU, RM_ALU: MEM_WB_ALUOut <= EX_MEM_ALUOut ; 
			
			LOAD		  : MEM_WB_LMD <= Mem[EX_MEM_ALUOut] ; 
			
			STORE         : if(TAKEN_BRANCH == 0 ) //Disabling Writing Function  
								Mem[EX_MEM_ALUOut] <= EX_MEM_B ; 
								
			default		  : MEM_WB_ALUOut <= 32'hxxxxxxxx ; 
			
		endcase 
		
	end 
	
//Write back Stage --- Stage 5

					
always @ (posedge clk1) 
	
	begin 
	
		if(TAKEN_BRANCH == 0) // Disable writing if branch is taken 
		
		case(MEM_WB_type)
		
		RR_ALU: RegBank[MEM_WB_IR[15:11]] <= MEM_WB_ALUOut ; // 'rd' 
		
		RM_ALU: RegBank[MEM_WB_IR[20:16]] <= MEM_WB_ALUOut ; // 'rt' 
		
		LOAD  : RegBank[MEM_WB_IR[20:16]] <= MEM_WB_LMD    ; // 'rt' in Load Instructions 
		
		HALT  : HALTED <= 1'b1 ;
		 
		endcase 
	
	end 


endmodule

Testing/Test1/Test1.v
//Adding three numbers 10, 20 and 30 stored in processor registers 

//Steps: 
//1. Initilize register R1 with 10
//2. Initilize register R2 with 20
//3. Initilize register R3 with 30 
//4. Add the three numbers and store the sum in R4 and R5


module Test1 ; 

reg clk1, clk2 ; 

integer k ; 

MIPS32 mips_testing1 ( clk1, clk2 ) ; 

//Generating 2 phase clocks 
initial 
	begin 
		clk1 = 0 ; 
		clk2 = 0 ; 
		
		repeat(80) //The program would be over by this
			begin 
				#5 clk1 = 1 ; 
				#5 clk1 = 0 ; 
				#5 clk2 = 1 ; 
				#5 clk2 = 0 ; 
			end 
	end 
	


//Programming the instructions inside the memory 
initial 

	begin 
		for(k=0; k<31; k++) 
			mips_testing1.RegBank[k] = k ; 
		
		//ADDI R1, R0, 10	
		mips_testing1.Mem[0] = 32'h2801000a ; 
		
		//ADDI R2 R0, 20 
		mips_testing1.Mem[1] = 32'h28020014 ; 
		
		//ADDI R3, R0, 25 
		mips_testing1.Mem[2] = 32'h28030019 ; 
		
		//Now we have to add 2 dummy instructions 
		//to wait for R2 to be stored
		
		//Dummy instruction -- OR R7, R7, R7 
		mips_testing1.Mem[3] = 32'h0ce77800 ; 
		
		//Dummy instruction -- OR R7, R7, R7 
		mips_testing1.Mem[4] = 32'h0ce77800 ; 
		
		//ADD R4, R1, R2
		mips_testing1.Mem[5] = 32'h00222000 ; 
		
		
		//This dummy instruction is for waiting
		//for correct data in R3
		//Dummy instruction -- OR R7, R7, R7 
		mips_testing1.Mem[6] = 32'h0ce77800 ; 
		
		//ADD R5, R4, R3 
		mips_testing1.Mem[7] = 32'h00832800 ;
		
		//HLT 
		mips_testing1.Mem[8] = 32'hfc000000 ; 
	
		//Initializing the working variables
		mips_testing1.HALTED = 0 ; 
		mips_testing1.PC = 0 ; 
		mips_testing1.TAKEN_BRANCH = 0 ; 
		
	end 
	
	initial 
		begin 
		
			$dumpfile ("mipstesting1.vcd") ; 
			$dumpvars (0, mips_testing1) ; 
				
				#400 $finish ; 
		end 
		
	initial 
		begin 
		
		#280 
		for( k = 0 ; k < 6 ; k++ ) 
			$display ("R%1d -- %2d", k, mips_testing1.RegBank[k]) ; 
		
		end
		
endmodule

Testing/Test1/mipstesting1.vcd
$date
	Sun Sep  6 11:17:17 2020
$end
$version
	Icarus Verilog
$end
$timescale
	1s
$end
$scope module Test1 $end
$scope module mips_testing1 $end
$var wire 1 ! clk1 $end
$var wire 1 " clk2 $end
$var reg 32 # EX_MEM_ALUOut [31:0] $end
$var reg 32 $ EX_MEM_B [31:0] $end
$var reg 32 % EX_MEM_IR [31:0] $end
$var reg 1 & EX_MEM_cond $end
$var reg 3 ' EX_MEM_type [2:0] $end
$var reg 1 ( HALTED $end
$var reg 32 ) ID_EX_A [31:0] $end
$var reg 32 * ID_EX_B [31:0] $end
$var reg 32 + ID_EX_IR [31:0] $end
$var reg 32 , ID_EX_Imm [31:0] $end
$var reg 32 - ID_EX_NPC [31:0] $end
$var reg 3 . ID_EX_type [2:0] $end
$var reg 32 / IF_ID_IR [31:0] $end
$var reg 32 0 IF_ID_NPC [31:0] $end
$var reg 32 1 MEM_WB_ALUOut [31:0] $end
$var reg 32 2 MEM_WB_IR [31:0] $end
$var reg 32 3 MEM_WB_LMD [31:0] $end
$var reg 3 4 MEM_WB_type [2:0] $end
$var reg 32 5 PC [31:0] $end
$var reg 1 6 TAKEN_BRANCH $end
$upscope $end
$upscope $end
$enddefinitions $end
#0
$dumpvars
06
b0 5
bx 4
bx 3
bx 2
bx 1
bx 0
bx /
bx .
bx -
bx ,
bx +
bx *
bx )
0(
bx '
x&
bx %
bx $
bx #
0"
0!
$end
#5
b1 5
b1 0
b101000000000010000000000001010 /
1!
#10
0!
#15
b1 .
b1010 ,
b101000000000010000000000001010 +
b1 -
b1 *
b0 )
1"
#20
0"
#25
b1010 #
b101000000000010000000000001010 %
b1 '
b10 5
b10 0
b101000000000100000000000010100 /
1!
#30
0!
#35
b1010 1
b101000000000010000000000001010 2
b1 4
b10100 ,
b101000000000100000000000010100 +
b10 -
b10 *
1"
#40
0"
#45
b11 5
b11 0
b101000000000110000000000011001 /
b10100 #
b101000000000100000000000010100 %
1!
#50
0!
#55
b11001 ,
b101000000000110000000000011001 +
b11 -
b11 *
b10100 1
b101000000000100000000000010100 2
1"
#60
0"
#65
b11001 #
b101000000000110000000000011001 %
b100 5
b100 0
b1100111001110111100000000000 /
1!
#70
0!
#75
b11001 1
b101000000000110000000000011001 2
b0 .
b111100000000000 ,
b1100111001110111100000000000 +
b100 -
b111 *
b111 )
1"
#80
0"
#85
b101 5
b101 0
b111 #
b1100111001110111100000000000 %
b0 '
1!
#90
0!
#95
b101 -
b111 1
b1100111001110111100000000000 2
b0 4
1"
#100
0"
#105
b110 5
b110 0
b1000100010000000000000 /
1!
#110
0!
#115
b10000000000000 ,
b1000100010000000000000 +
b110 -
b10100 *
b1010 )
1"
#120
0"
#125
b111 5
b111 0
b1100111001110111100000000000 /
b11110 #
b1000100010000000000000 %
1!
#130
0!
#135
b111100000000000 ,
b1100111001110111100000000000 +
b111 -
b111 *
b111 )
b11110 1
b1000100010000000000000 2
1"
#140
0"
#145
b111 #
b1100111001110111100000000000 %
b1000 5
b1000 0
b100000110010100000000000 /
1!
#150
0!
#155
b111 1
b1100111001110111100000000000 2
b10100000000000 ,
b100000110010100000000000 +
b1000 -
b11001 *
b11110 )
1"
#160
0"
#165
b1001 5
b1001 0
b11111100000000000000000000000000 /
b110111 #
b100000110010100000000000 %
1!
#170
0!
#175
b101 .
b0 ,
b11111100000000000000000000000000 +
b1001 -
b0 *
b0 )
b110111 1
b100000110010100000000000 2
1"
#180
0"
#185
b11111100000000000000000000000000 %
b101 '
b1010 5
b1010 0
bx /
1!
#190
0!
#195
bx 1
b11111100000000000000000000000000 2
b101 4
bx ,
bx +
b1010 -
bx *
bx )
1"
#200
0"
#205
b1011 5
b1011 0
bx %
1(
1!
