MIPS32.v
//MIPS32 Basic Implmentation 
//Engineer : Sat Patel 

module MIPS32 ( clk1, clk2 ) ; 

//Using two phase clock, for avoiding clashes and clock skews 

//Register Bank 
reg [31:0] RegBank [31:0] ; //Register bank ( 32 X 32 ) 

//Memory - 1024 x 32 
reg [31:0] Mem [1023:0] ; 

//Declaring the opcodes for the various instructions 
parameter ADD = 6'b000000 , SUB = 6'b000001, AND = 6'b000010, 
	OR = 6'b000011, SLT = 6'b000100, MUL = 6'b000101, HLT = 6'b111111, 
	LW = 6'b001000, SW = 6'b001001, ADDI = 6'b001010, SUBI = 6'b001011, 
	SLTI = 6'b001100, BNEQZ = 6'b001101, BEQZ = 6'b001110 ; 
	

//Types of instructions 
parameter RR_ALU = 3'b000, RM_ALU = 3'b001, LOAD = 3'b010, 
		STORE = 3'b011, BRANCH = 3'b100, HALT = 3'b101 ; 
		
reg [2:0] ID_EX_type, EX_MEM_type, MEM_WB_type ; 
		
reg HALTED ; 
//Set after HLT instruction is completed - in WB stage 

reg TAKEN_BRANCH ; 
//Required to disable instructions after branch 


//Defining intermediate latches between Instruction Fetch stage 
//and Instruction Decode stage 

reg [31:0] PC, IF_ID_IR, IF_ID_NPC ; 
//PC- Program Counter 
//IR - Instruction Register 
//NPC - Next Program Counter 

//Defining intermediate latches between Instruction Decode stage and 
//Execute stage 
reg [31:0] ID_EX_IR, ID_EX_NPC, ID_EX_A, ID_EX_B, ID_EX_Imm ; 

//Defining intermediate latches between Execute Stage and Memory Stage 
reg [31:0] EX_MEM_IR, EX_MEM_ALUOut, EX_MEM_B ; 
reg EX_MEM_cond ; 

//Defining intermediate latches between Memory Stage and Write back stage 
reg [31:0] MEM_WB_IR, MEM_WB_ALUOut, MEM_WB_LMD ; 

//Instruction Fetch Stage 

always @ ( posedge clk1 ) 

	if ( HALTED == 0 ) 
		begin 
			if(((EX_MEM_IR[31:26] == BEQZ) && (EX_MEM_cond == 1)) || ((EX_MEM_IR[31:26] == BNEQZ) && (EX_MEM_cond == 0))) 
				begin 
					IF_ID_IR <= Mem[EX_MEM_ALUOut] ; 
					TAKEN_BRANCH <= 1'b1 ; 
					IF_ID_NPC <= EX_MEM_ALUOut + 1 ; 
					PC <= EX_MEM_ALUOut + 1 ; 
				end 
		else 
			begin 
				IF_ID_IR <= Mem[PC] ; 
				IF_ID_NPC <= PC + 1 ; 
				PC <= PC + 1 ; 
			end 
		end 

//Instruction Decode Stage 

always @ ( posedge clk2 ) 

	if(HALTED == 0 ) 
		begin 
			if(IF_ID_IR[25:21] == 5'b00000) 
				ID_EX_A <= 0 ; 
			else 
				ID_EX_A <= RegBank[IF_ID_IR[25:21]] ; //"rs" 
			
			if(IF_ID_IR[20:16] == 5'b00000) 
				ID_EX_B <= 0 ; 
			else 
				ID_EX_B <= RegBank[IF_ID_IR[20:16]] ; //"rt" 
			
			ID_EX_NPC <= IF_ID_NPC ; 
			ID_EX_IR <= IF_ID_IR ; 
			ID_EX_Imm <= { {16{IF_ID_IR[15]} } , {IF_ID_IR[15:0] }} ; 
			
		case (IF_ID_IR[31:26]) 
			ADD, SUB, AND, OR, SLT, MUL:  ID_EX_type <= RR_ALU ; 
			ADDI, SUBI, SLTI: 			  ID_EX_type <= RM_ALU ; 
			LW: 						  ID_EX_type <= LOAD   ;
			SW: 						  ID_EX_type <= STORE  ;	 
			BNEQZ, BEQZ: 				  ID_EX_type <= BRANCH ;
			HLT: 						  ID_EX_type <= HALT   ;
			default: 					  ID_EX_type <= HALT   ;	
		endcase 
	end 




endmodule

Testing/Test3/Test3.v
module Test3 ; 

reg clk1, clk2 ; 
integer k ; 

MIPS32 mips_testing3 (clk1, clk2 ) ; 

initial 
	begin 
		clk1 = 0 ; 
		clk2 = 0 ; 
		
		repeat(50) 
			begin 
				#5 clk1 = 1 ; 
				#5 clk1 = 0 ; 
				#5 clk2 = 1 ; 
				#5 clk2 = 0 ; 
			end 
	end 
	
initial 
	begin 
		for(k=0 ; k <31 ; k = k + 1 ) 
			mips_testing3.RegBank[k] = k ; 

	//ADDI R10, R0, 200 
	mips_testing3.Mem[0] = 32'h280a00c8 ; 
	
	//ADDI R2, R0,1 
	mips_testing3.Mem[1] = 32'h28020001 ; 
	
	//Dummy Instruction 
	//OR R20, R20, R20 
	mips_testing3.Mem[2] = 32'h0e94a000 ; 
	
	//LW R3, 0(R10) 
	mips_testing3.Mem[3] = 32'h21430000 ; 
	
	//Dummy Instruction 
	//OR R20, R20, R20 
	mips_testing3.Mem[4] = 32'h0e94a000 ; 
	
	//Loop: MUL R2, R2, R3 
	mips_testing3.Mem[5] = 32'h14431000 ; 
	
	//SUBI R3, R3, 1 
	mips_testing3.Mem[6] = 32'h2c630001 ; 
	
	//Dummy Instruction 
	//OR R20, R20, R20 
	mips_testing3.Mem[7] = 32'h0e94a000 ; 
	
	//BNEQZ R3, loop ( -4 offset) 
	mips_testing3.Mem[8] = 32'h3460fffc ; 
	
	//SW R2, -2(R10) 
	mips_testing3.Mem[9] = 32'h2542fffe ; 
	
	//HLT
	mips_testing3.Mem[10] = 32'hfc000000 ; 
	
	//Find factorial of 7 
	mips_testing3.Mem[200] = 32'h00000007 ; 
	
	//Initializing the parameters 
	mips_testing3.PC = 0 ; 
	mips_testing3.HALTED = 0 ; 
	mips_testing3.TAKEN_BRANCH = 0 ; 
	
	#2000 $display ("Mem[200] = %2d, Mem[198] = %6d", mips_testing3.Mem[200] , mips_testing3.Mem[198] ) ; 
	
	end 

initial 
	begin 
		$dumpfile ("mipstesting3.vcd") ; 
		$dumpvars (0, Test3) ; 
		$monitor ("R2: %4d", mips_testing3.RegBank[2] ) ; 
		#3000 $finish ; 
	end 
	
endmodule

Testing/Test3/mipstesting3.vcd
$date
	Mon Sep  7 14:47:55 2020
$end
$version
	Icarus Verilog
$end
$timescale
	1s
$end
$scope module Test3 $end
$var reg 1 ! clk1 $end
$var reg 1 " clk2 $end
$var integer 32 # k [31:0] $end
$scope module mips_testing3 $end
$var wire 1 ! clk1 $end
$var wire 1 " clk2 $end
$var reg 32 $ EX_MEM_ALUOut [31:0] $end
$var reg 32 % EX_MEM_B [31:0] $end
$var reg 32 & EX_MEM_IR [31:0] $end
$var reg 1 ' EX_MEM_cond $end
$var reg 3 ( EX_MEM_type [2:0] $end
$var reg 1 ) HALTED $end
$var reg 32 * ID_EX_A [31:0] $end
$var reg 32 + ID_EX_B [31:0] $end
$var reg 32 , ID_EX_IR [31:0] $end
$var reg 32 - ID_EX_Imm [31:0] $end
$var reg 32 . ID_EX_NPC [31:0] $end
$var reg 3 / ID_EX_type [2:0] $end
$var reg 32 0 IF_ID_IR [31:0] $end
$var reg 32 1 IF_ID_NPC [31:0] $end
$var reg 32 2 MEM_WB_ALUOut [31:0] $end
$var reg 32 3 MEM_WB_IR [31:0] $end
$var reg 32 4 MEM_WB_LMD [31:0] $end
$var reg 3 5 MEM_WB_type [2:0] $end
$var reg 32 6 PC [31:0] $end
$var reg 1 7 TAKEN_BRANCH $end
$upscope $end
$upscope $end
$enddefinitions $end
#0
$dumpvars
07
b0 6
bx 5
bx 4
bx 3
bx 2
bx 1
bx 0
bx /
bx .
bx -
bx ,
bx +
bx *
0)
bx (
x'
bx &
bx %
bx $
b11111 #
0"
0!
$end
#5
b1 6
b1 1
b101000000010100000000011001000 0
1!
#10
0!
#15
b1 /
b11001000 -
b101000000010100000000011001000 ,
b1 .
b1010 +
b0 *
1"
#20
0"
#25
b11001000 $
b101000000010100000000011001000 &
b1 (
b10 6
b10 1
b101000000000100000000000000001 0
1!
#30
0!
#35
b11001000 2
b101000000010100000000011001000 3
b1 5
b1 -
b101000000000100000000000000001 ,
b10 .
b10 +
1"
#40
0"
#45
b11 6
b11 1
b1110100101001010000000000000 0
b1 $
b101000000000100000000000000001 &
1!
#50
0!
#55
b0 /
b11111111111111111010000000000000 -
b1110100101001010000000000000 ,
b11 .
b10100 +
b10100 *
b1 2
b101000000000100000000000000001 3
1"
#60
0"
#65
b10100 $
b1110100101001010000000000000 &
b0 (
b100 6
b100 1
b100001010000110000000000000000 0
1!
#70
0!
#75
b10100 2
b1110100101001010000000000000 3
b0 5
b10 /
b0 -
b100001010000110000000000000000 ,
b100 .
b11 +
b11001000 *
1"
#80
0"
#85
b101 6
b101 1
b1110100101001010000000000000 0
b11 %
b11001000 $
b100001010000110000000000000000 &
b10 (
1!
#90
0!
#95
b0 /
b11111111111111111010000000000000 -
b1110100101001010000000000000 ,
b101 .
b10100 +
b10100 *
b111 4
b100001010000110000000000000000 3
b10 5
1"
#100
0"
#105
b10100 $
b1110100101001010000000000000 &
b0 (
b110 6
b110 1
b10100010000110001000000000000 0
1!
#110
0!
#115
b1110100101001010000000000000 3
b0 5
b1000000000000 -
b10100010000110001000000000000 ,
b110 .
b111 +
b1 *
1"
#120
0"
#125
b111 6
b111 1
b101100011000110000000000000001 0
b111 $
b10100010000110001000000000000 &
1!
#130
0!
#135
b1 /
b1 -
b101100011000110000000000000001 ,
b111 .
b111 *
b111 2
b10100010000110001000000000000 3
1"
#140
0"
#145
b110 $
b101100011000110000000000000001 &
b1 (
b1000 6
b1000 1
b1110100101001010000000000000 0
1!
#150
0!
#155
b110 2
b101100011000110000000000000001 3
b1 5
b0 /
b11111111111111111010000000000000 -
b1110100101001010000000000000 ,
b1000 .
b10100 +
b10100 *
1"
#160
0"
#165
b1001 6
b1001 1
b110100011000001111111111111100 0
b10100 $
b1110100101001010000000000000 &
b0 (
1!
#170
0!
#175
b100 /
b11111111111111111111111111111100 -
b110100011000001111111111111100 ,
b1001 .
b0 +
b110 *
b10100 2
b1110100101001010000000000000 3
b0 5
1"
#180
0"
#185
0'
b101 $
b110100011000001111111111111100 &
b100 (
b1010 6
b1010 1
b100101010000101111111111111110 0
1!
#190
0!
#195
bx 2
b110100011000001111111111111100 3
b100 5
b11 /
b11111111111111111111111111111110 -
b100101010000101111111111111110 ,
b1010 .
b111 +
b11001000 *
1"
#200
0"
#205
b110 6
b110 1
17
b10100010000110001000000000000 0
b111 %
b11000110 $
b100101010000101111111111111110 &
b11 (
1!
#210
0!
#215
b0 /
b1000000000000 -
b10100010000110001000000000000 ,
b110 .
b110 +
b111 *
b100101010000101111111111111110 3
b11 5
1"
#220
0"
#225
b101010 $
07
b10100010000110001000000000000 &
b0 (
b111 6
b111 1
b101100011000110000000000000001 0
1!
#230
0!
#235
b101010 2
b10100010000110001000000000000 3
b0 5
b1 /
b1 -
b101100011000110000000000000001 ,
b111 .
b110 *
1"
#240
0"
#245
b1000 6
b1000 1
b1110100101001010000000000000 0
b101 $
b101100011000110000000000000001 &
b1 (
1!
#250
0!
#255
b0 /
b11111111111111111010000000000000 -
b1110100101001010000000000000 ,
b1000 .
b10100 +
b10100 *
b101 2
b101100011000110000000000000001 3
b1 5
1"
#260
0"
#265
b10100 $
b1110100101001010000000000000 &
b0 (
b1001 6
b1001 1
b110100011000001111111111111100 0
1!
#270
0!
#275
b10100 2
b1110100101001010000000000000 3
b0 5
b100 /
b11111111111111111111111111111100 -
b110100011000001111111111111100 ,
b1001 .
b0 +
b101 *
1"
#280
0"
#285
b1010 6
b1010 1
b100101010000101111111111111110 0
b101 $
b110100011000001111111111111100 &
b100 (
1!
#290
0!
#295
b11 /
b11111111111111111111111111111110 -
b100101010000101111111111111110 ,
b1010 .
b101010 +
b11001000 *
bx 2
b110100011000001111111111111100 3
b100 5
1"
#300
0"
#305
b101010 %
b11000110 $
b100101010000101111111111111110 &
b11 (
b110 6
b110 1
07
b10100010000110001000000000000 0
1!
#310
0!
#315
b100101010000101111111111111110 3
b11 5
b0 /
b1000000000000 -
b10100010000110001000000000000 ,
b110 .
b101 +
b101010 *
1"
#320
0"
#325
b111 6
b111 1
b101100011000110000000000000001 0
b11010010 $
b10100010000110001000000000000 &
b0 (
1!
#330
0!
#335
b1 /
b1 -
b101100011000110000000000000001 ,
b111 .
b101 *
b11010010 2
b10100010000110001000000000000 3
b0 5
1"
#340
0"
#345
b100 $
b101100011000110000000000000001 &
b1 (
b1000 6
b1000 1
b1110100101001010000000000000 0
1!
#350
0!
#355
b100 2
b101100011000110000000000000001 3
b1 5
b0 /
b11111111111111111010000000000000 -
b1110100101001010000000000000 ,
b1000 .
b10100 +
b10100 *
1"
#360
0"
#365
b1001 6
b1001 1
b110100011000001111111111111100 0
b10100 $
b1110100101001010000000000000 &
b0 (
1!
#370
0!
#375
b100 /
b11111111111111111111111111111100 -
b110100011000001111111111111100 ,
b1001 .
b0 +
b100 *
b10100 2
b1110100101001010000000000000 3
b0 5
1"
#380
0"
#385
b101 $
b110100011000001111111111111100 &
b100 (
b1010 6
b1010 1
b100101010000101111111111111110 0
1!
#390
0!
#395
bx 2
b110100011000001111111111111100 3
b100 5
b11 /
b11111111111111111111111111111110 -
b100101010000101111111111111110 ,
b1010 .
b11010010 +
b11001000 *
1"
#400
0"
#405
b110 6
b110 1
17
b10100010000110001000000000000 0
b11010010 %
b11000110 $
b100101010000101111111111111110 &
b11 (
1!
#410
0!
#415
b0 /
b1000000000000 -
b10100010000110001000000000000 ,
b110 .
b100 +
b11010010 *
b100101010000101111111111111110 3
b11 5
1"
#420
0"
#425
b1101001000 $
07
b10100010000110001000000000000 &
b0 (
b111 6
b111 1
b101100011000110000000000000001 0
1!
#430
0!
#435
b1101001000 2
b10100010000110001000000000000 3
b0 5
b1 /
b1 -
b101100011000110000000000000001 ,
b111 .
b100 *
1"
#440
0"
#445
b1000 6
b1000 1
b1110100101001010000000000000 0
b11 $
b101100011000110000000000000001 &
b1 (
1!
#450
0!
#455
b0 /
b11111111111111111010000000000000 -
b1110100101001010000000000000 ,
b1000 .
b10100 +
b10100 *
b11 2
b101100011000110000000000000001 3
b1 5
1"
#460
0"
#465
b10100 $
b1110100101001010000000000000 &
b0 (
b1001 6
b1001 1
b110100011000001111111111111100 0
1!
#470
0!
#475
b10100 2
b1110100101001010000000000000 3
b0 5
b100 /
b11111111111111111111111111111100 -
b110100011000001111111111111100 ,
b1001 .
b0 +
b11 *
1"
#480
0"
#485
b1010 6
b1010 1
b100101010000101111111111111110 0
b101 $
b110100011000001111111111111100 &
b100 (
1!
#490
0!
#495
b11 /
b11111111111111111111111111111110 -
b100101010000101111111111111110 ,
b1010 .
b1101001000 +
b11001000 *
bx 2
b110100011000001111111111111100 3
b100 5
1"
#500
0"
#505
b1101001000 %
b11000110 $
b100101010000101111111111111110 &
b11 (
b110 6
b110 1
07
b10100010000110001000000000000 0
1!
#510
0!
#515
b100101010000101111111111111110 3
b11 5
b0 /
b1000000000000 -
b10100010000110001000000000000 ,
b110 .
b11 +
b1101001000 *
1"
#520
0"
#525
b111 6
b111 1
b101100011000110000000000000001 0
b100111011000 $
b10100010000110001000000000000 &
b0 (
1!
#530
0!
#535
b1 /
b1 -
b101100011000110000000000000001 ,
b111 .
b11 *
b100111011000 2
b10100010000110001000000000000 3
b0 5
1"
#540
0"
#545
b10 $
b101100011000110000000000000001 &
b1 (
b1000 6
b1000 1
b1110100101001010000000000000 0
1!
#550
0!
#555
b10 2
b101100011000110000000000000001 3
b1 5
b0 /
b11111111111111111010000000000000 -
b1110100101001010000000000000 ,
b1000 .
b10100 +
b10100 *
1"
#560
0"
#565
b1001 6
b1001 1
b110100011000001111111111111100 0
b10100 $
b1110100101001010000000000000 &
b0 (
1!
#570
0!
#575
b100 /
b11111111111111111111111111111100 -
b110100011000001111111111111100 ,
b1001 .
b0 +
b10 *
b10100 2
b1110100101001010000000000000 3
b0 5
1"
#580
0"
#585
b101 $
b110100011000001111111111111100 &
b100 (
b1010 6
b1010 1
b100101010000101111111111111110 0
1!
#590
0!
#595
bx 2
b110100011000001111111111111100 3
b100 5
b11 /
b11111111111111111111111111111110 -
b100101010000101111111111111110 ,
b1010 .
b100111011000 +
b11001000 *
1"
#600
0"
#605
b110 6
b110 1
17
b10100010000110001000000000000 0
b100111011000 %
b11000110 $
b100101010000101111111111111110 &
b11 (
1!
#610
0!
#615
b0 /
b1000000000000 -
b10100010000110001000000000000 ,
b110 .
b10 +
b100111011000 *
b100101010000101111111111111110 3
b11 5
1"
#620
0"
#625
b1001110110000 $
07
b10100010000110001000000000000 &
b0 (
b111 6
b111 1
b101100011000110000000000000001 0
1!
#630
0!
#635
b1001110110000 2
b10100010000110001000000000000 3
b0 5
b1 /
b1 -
b101100011000110000000000000001 ,
b111 .
b10 *
1"
#640
0"
#645
b1000 6
b1000 1
b1110100101001010000000000000 0
b1 $
b101100011000110000000000000001 &
b1 (
1!
#650
0!
#655
b0 /
b11111111111111111010000000000000 -
b1110100101001010000000000000 ,
b1000 .
b10100 +
b10100 *
b1 2
b101100011000110000000000000001 3
b1 5
1"
#660
0"
#665
b10100 $
b1110100101001010000000000000 &
b0 (
b1001 6
b1001 1
b110100011000001111111111111100 0
1!
#670
0!
#675
b10100 2
b1110100101001010000000000000 3
b0 5
b100 /
b11111111111111111111111111111100 -
b110100011000001111111111111100 ,
b1001 .
b0 +
b1 *
1"
#680
0"
#685
b1010 6
b1010 1
b100101010000101111111111111110 0
b101 $
b110100011000001111111111111100 &
b100 (
1!
#690
0!
#695
b11 /
b11111111111111111111111111111110 -
b100101010000101111111111111110 ,
b1010 .
b1001110110000 +
b11001000 *
bx 2
b110100011000001111111111111100 3
b100 5
1"
#700
0"
#705
b1001110110000 %
b11000110 $
b100101010000101111111111111110 &
b11 (
b110 6
b110 1
07
b10100010000110001000000000000 0
1!
#710
0!
#715
b100101010000101111111111111110 3
b11 5
b0 /
b1000000000000 -
b10100010000110001000000000000 ,
b110 .
b1 +
b1001110110000 *
1"
#720
0"
#725
b111 6
b111 1
b101100011000110000000000000001 0
b1001110110000 $
b10100010000110001000000000000 &
b0 (
1!
#730
0!
#735
b1 /
b1 -
b101100011000110000000000000001 ,
b111 .
b1 *
b1001110110000 2
b10100010000110001000000000000 3
b0 5
1"
#740
0"
#745
b0 $
b101100011000110000000000000001 &
b1 (
b1000 6
b1000 1
b1110100101001010000000000000 0
1!
#750
0!
#755
b0 2
b101100011000110000000000000001 3
b1 5
b0 /
b11111111111111111010000000000000 -
b1110100101001010000000000000 ,
b1000 .
b10100 +
b10100 *
1"
#760
0"
#765
b1001 6
b1001 1
b110100011000001111111111111100 0
b10100 $
b1110100101001010000000000000 &
b0 (
1!
#770
0!
#775
b100 /
b11111111111111111111111111111100 -
b110100011000001111111111111100 ,
b1001 .
b0 +
b0 *
b10100 2
b1110100101001010000000000000 3
b0 5
1"
#780
0"
#785
1'
b101 $
b110100011000001111111111111100 &
b100 (
b1010 6
b1010 1
b100101010000101111111111111110 0
1!
#790
0!
#795
bx 2
b110100011000001111111111111100 3
b100 5
b11 /
b11111111111111111111111111111110 -
b100101010000101111111111111110 ,
b1010 .
b1001110110000 +
b11001000 *
1"
#800
0"
#805
b1011 6
b1011 1
b11111100000000000000000000000000 0
b11000110 $
b100101010000101111111111111110 &
b11 (
1!
#810
0!
#815
b101 /
b0 -
b11111100000000000000000000000000 ,
b1011 .
b0 +
b0 *
b100101010000101111111111111110 3
b11 5
1"
#820
0"
#825
b11111100000000000000000000000000 &
b101 (
b1100 6
b1100 1
bx 0
1!
#830
0!
#835
b11111100000000000000000000000000 3
b101 5
bx -
bx ,
b1100 .
bx +
bx *
1"
#840
0"
#845
b1101 6
b1101 1
bx &
1)
1!
